vme_cli/__init__.py
vme_cli/_version.py
vme_cli/constants.py
vme_cli/main.py
vme_cli/audio/__init__.py
vme_cli/audio/dependency_check.py
vme_cli/audio/factory.py
vme_cli/audio/flexible_audio_manager.py
vme_cli/audio/manager.py
vme_cli/audio/mock_manager.py
vme_cli/audio/real_manager.py
vme_cli/audio/simple_manager.py
vme_cli/audio/simple_realtime_manager.py
vme_cli/audio/utils.py
vme_cli/config/__init__.py
vme_cli/config/default_config.yaml
vme_cli/config/settings.py
vme_cli/llm/__init__.py
vme_cli/llm/manager.py
vme_cli/mcp/__init__.py
vme_cli/mcp/manager.py
vme_cli/testing/__init__.py
vme_cli/testing/integration_test.py
vme_cli/testing/session_test_framework.py
vme_cli/ui/__init__.py
vme_cli/ui/app.py
vme_cli/ui/audio_widgets.py
vme_cli/ui/simple_audio_widgets.py
vme_mcp_cli-0.1.9.dist-info/METADATA
vme_mcp_cli-0.1.9.dist-info/WHEEL
vme_mcp_cli-0.1.9.dist-info/entry_points.txt
vme_mcp_cli-0.1.9.dist-info/top_level.txt
vme_mcp_cli-0.1.9.dist-info/RECORD
