Metadata-Version: 2.4
Name: vme-mcp-cli
Version: 0.1.9
Summary: VME Infrastructure Management CLI Tool - Chat interface with voice commands
Project-URL: Homepage, https://github.com/frippe75/vme-fastmcp-server-v2
Project-URL: Repository, https://github.com/frippe75/vme-fastmcp-server-v2
Project-URL: Issues, https://github.com/frippe75/vme-fastmcp-server-v2/issues
Requires-Python: >=3.10
Requires-Dist: anthropic>=0.54.0
Requires-Dist: openai>=1.0.0
Requires-Dist: fastmcp>=2.8.1
Requires-Dist: click>=8.0.0
Requires-Dist: textual==0.85.2
Requires-Dist: rich>=13.0.0
Requires-Dist: pyyaml>=6.0.2
Requires-Dist: python-dotenv>=1.1.0
Requires-Dist: websockets<14.0
Requires-Dist: httpx>=0.25.0
Provides-Extra: audio
Requires-Dist: pyaudio>=0.2.11; extra == "audio"
Requires-Dist: sounddevice>=0.4.0; extra == "audio"
Requires-Dist: soundfile>=0.12.0; extra == "audio"
Requires-Dist: numpy>=1.20.0; extra == "audio"
Provides-Extra: dev
Requires-Dist: pytest>=7.0.0; extra == "dev"
Requires-Dist: pytest-asyncio>=0.21.0; extra == "dev"
Requires-Dist: black>=23.0.0; extra == "dev"
Requires-Dist: isort>=5.12.0; extra == "dev"
